check_syncrepl_extended/__init__.py
check_syncrepl_extended/check_syncrepl_extended.py
check_syncrepl_extended-2020.13.1.dist-info/LICENSE
check_syncrepl_extended-2020.13.1.dist-info/METADATA
check_syncrepl_extended-2020.13.1.dist-info/WHEEL
check_syncrepl_extended-2020.13.1.dist-info/top_level.txt
check_syncrepl_extended-2020.13.1.dist-info/RECORD
