Metadata-Version: 2.1
Name: check-syncrepl-extended
Version: 2020.13.1
Summary: Script to check LDAP syncrepl replication state between two servers
Home-page: https://gitlab.ics.muni.cz/perun-proxy-aai/python/check_syncrepl_extended.git
License: UNKNOWN
Platform: UNKNOWN
Requires-Python: >=3.9
Requires-Dist: python-ldap (~=3.4)
